quizard_generator/__init__.py
quizard_generator/__main__.py
quizard_generator/_version.py
quizard_generator/cli.py
quizard_generator/config.py
quizard_generator/exceptions.py
quizard_generator/commands/__init__.py
quizard_generator/commands/generate.py
quizard_generator/commands/index.py
quizard_generator/commands/list_domains.py
quizard_generator/commands/validate.py
quizard_generator/extractors/__init__.py
quizard_generator/extractors/concept_extractor.py
quizard_generator/extractors/question_seed_extractor.py
quizard_generator/generators/__init__.py
quizard_generator/generators/questions.py
quizard_generator/indexing/__init__.py
quizard_generator/indexing/domain_manager.py
quizard_generator/indexing/index_manifest.py
quizard_generator/knowledge/__init__.py
quizard_generator/knowledge/retriever.py
quizard_generator/knowledge/summariser.py
quizard_generator/models/__init__.py
quizard_generator/models/enums.py
quizard_generator/models/quiz_models.py
quizard_generator/models/response_schemas.py
quizard_generator/pipeline/__init__.py
quizard_generator/pipeline/core.py
quizard_generator/providers/__init__.py
quizard_generator/providers/factory.py
quizard_generator-0.1.0.dist-info/licenses/LICENSE
quizard_generator-0.1.0.dist-info/METADATA
quizard_generator-0.1.0.dist-info/WHEEL
quizard_generator-0.1.0.dist-info/entry_points.txt
quizard_generator-0.1.0.dist-info/top_level.txt
quizard_generator-0.1.0.dist-info/RECORD
