Metadata-Version: 2.4
Name: quizard-generator
Version: 0.1.0
Summary: A domain-based quiz generation system using LlamaIndex and LLMs
Author-email: Timothy Chia Kai Lun <timothy.ckl@outlook.com>
License: MIT
Project-URL: Homepage, https://github.com/timothyckl/quizard-generator
Project-URL: Repository, https://github.com/timothyckl/quizard-generator
Project-URL: Documentation, https://github.com/timothyckl/quizard-generator#readme
Project-URL: Bug Tracker, https://github.com/timothyckl/quizard-generator/issues
Keywords: quiz,education,llm,llamaindex,question-generation
Classifier: Development Status :: 3 - Alpha
Classifier: Intended Audience :: Developers
Classifier: Intended Audience :: Education
Classifier: License :: OSI Approved :: MIT License
Classifier: Programming Language :: Python :: 3
Classifier: Programming Language :: Python :: 3.9
Classifier: Programming Language :: Python :: 3.10
Classifier: Programming Language :: Python :: 3.11
Classifier: Programming Language :: Python :: 3.12
Classifier: Topic :: Education
Classifier: Topic :: Software Development :: Libraries :: Python Modules
Requires-Python: >=3.9
License-File: LICENSE
Requires-Dist: llama-index-core>=0.14.10
Requires-Dist: llama-index-llms-ollama>=0.9.0
Requires-Dist: llama-index-embeddings-ollama>=0.8.4
Requires-Dist: llama-index-readers-file>=0.5.5
Requires-Dist: pyyaml>=6.0
Provides-Extra: dev
Requires-Dist: pytest>=7.0; extra == "dev"
Requires-Dist: pytest-asyncio>=0.21.0; extra == "dev"
Requires-Dist: black>=23.0; extra == "dev"
Requires-Dist: ruff>=0.1.0; extra == "dev"
Requires-Dist: mypy>=1.0; extra == "dev"
Dynamic: license-file
